xrd_xy_parser/__init__.py
xrd_xy_parser/xy.py
xrd_xy_parser-0.0.4.dist-info/LICENSE
xrd_xy_parser-0.0.4.dist-info/METADATA
xrd_xy_parser-0.0.4.dist-info/WHEEL
xrd_xy_parser-0.0.4.dist-info/top_level.txt
xrd_xy_parser-0.0.4.dist-info/RECORD
