Metadata-Version: 2.1
Name: xrd-xy-parser
Version: 0.0.4
Summary: parse xy format file of X-ray diffraction
Project-URL: Homepage, https://gitlab.com/oksongh/xrd-xy-parser
Classifier: Programming Language :: Python :: 3
Classifier: License :: OSI Approved :: MIT License
Classifier: Operating System :: OS Independent
Requires-Python: >=3.10
License-File: LICENSE
Requires-Dist: numpy
